lethargy/__init__.py
lethargy/errors.py
lethargy/mixins.py
lethargy/options.py
lethargy/util.py
lethargy-3.1.0.dist-info/LICENSE
lethargy-3.1.0.dist-info/WHEEL
lethargy-3.1.0.dist-info/METADATA
lethargy-3.1.0.dist-info/RECORD
