Metadata-Version: 2.1
Name: lethargy
Version: 3.1.0
Summary: A minimal library to make your option-parsing easier.
Home-page: https://github.com/SeparateRecords/lethargy
License: MIT
Keywords: CLI,options,scripting,arguments,minimal
Author: SeparateRecords
Author-email: me@rob.ac
Requires-Python: >=3.6,<4.0
Classifier: Development Status :: 5 - Production/Stable
Classifier: Environment :: Console
Classifier: Intended Audience :: Developers
Classifier: License :: OSI Approved :: MIT License
Classifier: Programming Language :: Python :: 3
Classifier: Programming Language :: Python :: 3.6
Classifier: Programming Language :: Python :: 3.7
Classifier: Programming Language :: Python :: 3.8
Project-URL: Repository, https://github.com/SeparateRecords/lethargy
